codegen/cli/__init__.py
codegen/cli/cli.py
codegen/cli/errors.py
codegen/cli/api/client.py
codegen/cli/api/endpoints.py
codegen/cli/api/modal.py
codegen/cli/api/schemas.py
codegen/cli/api/webapp_routes.py
codegen/cli/auth/constants.py
codegen/cli/auth/decorators.py
codegen/cli/auth/login.py
codegen/cli/auth/session.ipynb
codegen/cli/auth/session.py
codegen/cli/auth/token_manager.ipynb
codegen/cli/auth/token_manager.py
codegen/cli/codemod/convert.py
codegen/cli/commands/create/main.py
codegen/cli/commands/deploy/main.py
codegen/cli/commands/docs_search/main.py
codegen/cli/commands/expert/main.py
codegen/cli/commands/init/main.py
codegen/cli/commands/init/render.py
codegen/cli/commands/list/main.py
codegen/cli/commands/login/main.py
codegen/cli/commands/logout/main.py
codegen/cli/commands/profile/main.py
codegen/cli/commands/run/main.ipynb
codegen/cli/commands/run/main.py
codegen/cli/commands/run/render.ipynb
codegen/cli/commands/run/render.py
codegen/cli/commands/run_on_pr/main.py
codegen/cli/commands/style_debug/main.py
codegen/cli/env/constants.py
codegen/cli/env/enums.py
codegen/cli/env/global_env.ipynb
codegen/cli/env/global_env.py
codegen/cli/git/folder.py
codegen/cli/git/patch.ipynb
codegen/cli/git/patch.py
codegen/cli/git/reop.ipynb
codegen/cli/git/repo.py
codegen/cli/git/url.ipynb
codegen/cli/git/url.py
codegen/cli/rich/codeblocks.py
codegen/cli/rich/pretty_print.py
codegen/cli/rich/spinners.py
codegen/cli/sdk/__init__.py
codegen/cli/sdk/decorator.py
codegen/cli/sdk/function.py
codegen/cli/sdk/functions.py
codegen/cli/sdk/models.py
codegen/cli/sdk/pull_request.py
codegen/cli/utils/codemod_manager.py
codegen/cli/utils/codemods.py
codegen/cli/utils/config.py
codegen/cli/utils/constants.py
codegen/cli/utils/count_functions.py
codegen/cli/utils/count_functions_2.py
codegen/cli/utils/function_finder.py
codegen/cli/utils/json_schema.py
codegen/cli/utils/schema.ipynb
codegen/cli/utils/schema.py
codegen/cli/utils/url.py
codegen/cli/workspace/decorators.py
codegen-1.24.1.dist-info/METADATA
codegen-1.24.1.dist-info/WHEEL
codegen-1.24.1.dist-info/entry_points.txt
codegen-1.24.1.dist-info/licenses/LICENSE
codegen-1.24.1.dist-info/RECORD
