Metadata-Version: 2.4
Name: codegen
Version: 1.24.1
Summary: CLI tool for code refactoring
Author-email: Codegen Team <team@codegen.com>
License: Apache-2.0
License-File: LICENSE
Classifier: Development Status :: 4 - Beta
Classifier: Environment :: MacOS X
Classifier: Intended Audience :: Developers
Classifier: License :: OSI Approved :: Apache Software License
Classifier: Programming Language :: Python
Classifier: Programming Language :: Python :: 3
Classifier: Programming Language :: Python :: 3.13
Classifier: Topic :: Software Development
Requires-Python: >=3.13
Requires-Dist: algoliasearch
Requires-Dist: click
Requires-Dist: codegen-types>=0.263.0
Requires-Dist: datamodel-code-generator>=0.26.5
Requires-Dist: giturlparse
Requires-Dist: graph-sitter[types]>=6.6.5
Requires-Dist: pathlib
Requires-Dist: posthog
Requires-Dist: pydantic>=2.10.3
Requires-Dist: pygit2>=1.16.0
Requires-Dist: python-dotenv>=1.0.1
Requires-Dist: requests
Requires-Dist: rich
Requires-Dist: rich-click>=1.8.5
Requires-Dist: toml>=0.10.2
Requires-Dist: unidiff>=0.7.5
